playgroundtools/__init__.py
playgroundtools/__main__.py
playgroundtools/cli.py
playgroundtools/commands.py
playgroundtools/config.json
playgroundtools/exceptions.py
playgroundtools/gui.py
playgroundtools/metadata.py
playgroundtools/playground.py
playgroundtools/resources.py
playgroundtools/util.py
playgroundtools/views/__init__.py
playgroundtools/views/about.py
playgroundtools/views/delete.py
playgroundtools/views/dialog.py
playgroundtools/views/directory.py
playgroundtools/views/file.py
playgroundtools/views/main.py
playgroundtools/views/new.py
tests/__init__.py
tests/fixtures.py
tests/test_commands.py
tests/test_playground.py
tests/test_util.py
playgroundtools-1.10.1.dist-info/LICENSE
playgroundtools-1.10.1.dist-info/METADATA
playgroundtools-1.10.1.dist-info/WHEEL
playgroundtools-1.10.1.dist-info/entry_points.txt
playgroundtools-1.10.1.dist-info/top_level.txt
playgroundtools-1.10.1.dist-info/RECORD
