Metadata-Version: 2.1
Name: playgroundtools
Version: 1.10.1
Summary: An interface for managing playground projects.
Home-page: https://github.com/saibalusulapalem/playgroundtools
Author: saibalusulapalem
Author-email: sai.balusulapalem@gmail.com
License: MIT License
Project-URL: Bug Tracker, https://github.com/saibalusulapalem/playgroundtools/issues
Keywords: sandbox,project,files
Classifier: Intended Audience :: End Users/Desktop
Classifier: Operating System :: Microsoft :: Windows
Classifier: Operating System :: MacOS
Classifier: Operating System :: POSIX :: Linux
Classifier: Programming Language :: Python :: 3
Classifier: Programming Language :: Python :: 3.9
Classifier: Programming Language :: Python :: 3.10
License-File: LICENSE
Provides-Extra: dev
Requires-Dist: black ; extra == 'dev'
Requires-Dist: isort ; extra == 'dev'
Provides-Extra: test
Requires-Dist: pytest ; extra == 'test'
Requires-Dist: flake8 ; extra == 'test'
